{
  "hash": "c95b784d",
  "configHash": "8c77b513",
  "lockfileHash": "9a1b0088",
  "browserHash": "384d907f",
  "optimized": {
    "react": {
      "src": "../../node_modules/react/index.js",
      "file": "react.js",
      "fileHash": "fe02b822",
      "needsInterop": true
    },
    "react-dom/client": {
      "src": "../../node_modules/react-dom/client.js",
      "file": "react-dom_client.js",
      "fileHash": "d8ff173a",
      "needsInterop": true
    }
  },
  "chunks": {
    "chunk-SS3IWWB5": {
      "file": "chunk-SS3IWWB5.js"
    }
  }
}